{
  "$schema" : "mega-manipulator-schema.json",
  "concurrency" : 1,
  "searchHostSettings" : {
    "github": {
      "gitHub": {
        "username": "jensim"
      }
    },
    "sourcegraph_com" : {
      "sourceGraph" : {
        "username": "jensim",
        "codeHostSettings" : {
          "github.com" : {
            "gitHub" : {
              "username" : "jensim"
            }
          }
        }
      }
    },
    "private_sourcegraph" : {
      "sourceGraph" : {
        "username": "jensim",
        "baseUrl" : "http://localhost:7080",
        "httpsOverride": "ALLOW_ANYTHING",
        "codeHostSettings" : {
          "github.com" : {
            "gitHub" : {
              "username" : "jensim"
            }
          },
          "bitbucket" : {
            "bitBucket" : {
              "baseUrl" : "http://localhost:7081",
              "httpsOverride": "ALLOW_ANYTHING",
              "username" : "jensim"
            }
          },
          "gitlab.com" : {
            "gitLab" : {
              "username" : "jensim"
            }
          }
        }
      }
    }
  }
}
